ipwhere/__init__.py
ipwhere-2.0.3.dist-info/LICENSE.txt
ipwhere-2.0.3.dist-info/METADATA
ipwhere-2.0.3.dist-info/WHEEL
ipwhere-2.0.3.dist-info/entry_points.txt
ipwhere-2.0.3.dist-info/top_level.txt
ipwhere-2.0.3.dist-info/RECORD
