Metadata-Version: 2.1
Name: ipwhere
Version: 2.0.3
Summary: ipwhere - query an IP address geographical location
Author-email: Eugene Ciurana pr3d4t0r <ipwhere.project@cime.net>
License: BSD-3-Clause
Classifier: Intended Audience :: Other Audience
Classifier: Operating System :: MacOS
Classifier: Operating System :: Unix
Classifier: Programming Language :: Python :: 3
Classifier: Programming Language :: Python :: 3.9
Requires-Python: >=3.9.9
License-File: LICENSE.txt
Requires-Dist: appdirs
Requires-Dist: click
Requires-Dist: psutil
Requires-Dist: pyperclip
